README.md
nbmc.py
setup.py
nbmc.egg-info/PKG-INFO
nbmc.egg-info/SOURCES.txt
nbmc.egg-info/dependency_links.txt
nbmc.egg-info/requires.txt
nbmc.egg-info/top_level.txt